<?xml version="1.0" encoding="utf-8" ?>
<Defs>
	<!-- carniculus -->
	<ThingDef ParentName="rjw_BodyPartNaturalBase">
		<defName>CarniPenis</defName>
		<label>carniculus penis</label>
		<description>monster penis</description>
		<graphicData>
			<texPath>Things/Item/Parts/genital_male</texPath>
			<graphicClass>Graphic_Single</graphicClass>
		</graphicData>
		<statBases>
			<MarketValue>250</MarketValue>
			<Mass>1.2</Mass>
		</statBases>
	</ThingDef>
	
	<ThingDef ParentName="rjw_BodyPartNaturalBase">
		<defName>CarniVagina</defName>
		<label>carniculus vagina</label>
		<description>big vagina</description>
		<graphicData>
			<texPath>Things/Item/Parts/genital_female</texPath>
			<graphicClass>Graphic_Single</graphicClass>
		</graphicData>
		<statBases>
			<MarketValue>250</MarketValue>
			<Mass>0.10</Mass>
		</statBases>
	</ThingDef>
	
	<ThingDef ParentName="rjw_BodyPartNaturalBase">
		<defName>CarniBreasts</defName>
		<label>carniculus breasts</label>
		<description>big breasts</description>
		<graphicData>
			<texPath>Things/Item/Parts/breast</texPath>
			<graphicClass>Graphic_Single</graphicClass>
		</graphicData>
		<statBases>
			<MarketValue>250</MarketValue>
			<Mass>0.10</Mass>
		</statBases>
	</ThingDef>
	
</Defs>